{
  "version": 8,
  "name": "Water network",
  "center": [
    -64.405087,
    -34.919628
  ],
  "height": "600px",
  "zoom": 4,
  "bearing": 0,
  "pitch": 0,
  "sources": {
    "boundaries": {
      "type": "vector",
      "url": "mbtiles://{boundaries}"
    },
    "water": {
      "type": "vector",
      "url": "mbtiles://{water}"
    }
  },
  "glyphs": "{fontstack}/{range}.pbf",
  "layers": [
    {
      "id": "background",
      "type": "background",
      "paint": {
        "background-color": "#c6e1ff"
      }
    },
    {
      "id": "landuse-neighbour",
      "type": "fill",
      "source": "boundaries",
      "source-layer": "admin_0_boundaries",
      "paint": {
        "fill-color": "#e0e0e0"
      }
    },
    {
      "id": "landuse-neighbour-borders",
      "type": "line",
      "source": "boundaries",
      "source-layer": "admin_0_boundaries",
      "paint": {
        "line-color": "#ffffff",
        "line-width": 2
      }
    },
    {
      "id": "landuse",
      "type": "fill",
      "source": "boundaries",
      "source-layer": "admin_1_boundaries",
      "paint": {
        "fill-color": "#d2d2d2"
      }
    },
    {
      "id": "landuse-borders",
      "type": "line",
      "source": "boundaries",
      "source-layer": "admin_1_boundaries",
      "paint": {
        "line-color": "#ffffff",
        "line-width": 2
      }
    },
    {
      "id": "water",
      "type": "fill",
      "source": "boundaries",
      "source-layer": "physical_lakes",
      "paint": {
        "fill-color": "#c6e1ff"
      }
    },
    {
      "id": "country_labels",
      "type": "symbol",
      "source": "boundaries",
      "source-layer": "admin_0_boundaries_labels",
      "layout": {
        "text-field": "{name}",
        "symbol-placement": "point"
      },
      "maxzoom": 4
    },
    {
      "id": "provinces_labels",
      "type": "symbol",
      "source": "boundaries",
      "source-layer": "admin_1_boundaries_labels",
      "layout": {
        "text-field": "{name}",
        "symbol-placement": "point"
      },
      "minzoom": 4
    },
    {
      "id": "waterway",
      "type": "line",
      "source": "water",
      "source-layer": "water_edges",
      "paint": {
        "line-color": "#045a8d",
        "line-width": {
          "base": 1.4,
          "stops": [
            [
              11,
              4
            ],
            [
              17,
              50
            ]
          ]
        }
      }
    }
  ]
}